WeiboCrawl2/VERSION.txt
WeiboCrawl2/__init__.py
WeiboCrawl2/config.json
WeiboCrawl2/logging.conf
WeiboCrawl2/weibo.py
weibocrawl2-0.0.5.dist-info/METADATA
weibocrawl2-0.0.5.dist-info/WHEEL
weibocrawl2-0.0.5.dist-info/top_level.txt
weibocrawl2-0.0.5.dist-info/RECORD
