Metadata-Version: 2.1
Name: weibocrawl2
Version: 0.0.5
Summary: download data of weibo
Home-page: http://iseuwei.org
Author: Iseuwei
Author-email: iseu1130@sina.cn
License: BSD
Keywords: WeiboCrawl2
Platform: UNKNOWN
Classifier: Development Status :: 4 - Beta
Classifier: Programming Language :: Python :: 2.6
Classifier: Programming Language :: Python :: 2.7
Classifier: Programming Language :: Python :: 3.2
Classifier: Programming Language :: Python :: 3.3
Classifier: Programming Language :: Python :: 3.4
Classifier: Programming Language :: Python :: 3.5
Classifier: License :: OSI Approved :: BSD License
Requires-Dist: pandas (>=0.18.0)
Requires-Dist: requests (>=2.0.0)
Requires-Dist: lxml (>=3.8.0)
Requires-Dist: simplejson (>=3.16.0)
Requires-Dist: msgpack (>=0.5.6)
Requires-Dist: pyzmq (>=16.0.0)
